Analyze.py
Analyze-1.0.0.dist-info/LICENSE
Analyze-1.0.0.dist-info/METADATA
Analyze-1.0.0.dist-info/WHEEL
Analyze-1.0.0.dist-info/top_level.txt
Analyze-1.0.0.dist-info/RECORD
